ml4pd/__init__.py
ml4pd/_components.py
ml4pd/_registry.py
ml4pd/flowsheet.py
ml4pd/utils.py
ml4pd/aspen_units/__init__.py
ml4pd/aspen_units/distillation.py
ml4pd/aspen_units/flash.py
ml4pd/aspen_units/unit.py
ml4pd/aspen_units/utils.py
ml4pd/data/__init__.py
ml4pd/data/aspen_constants.csv
ml4pd/data/rdkit_features.txt
ml4pd/data/thermo_dict.json
ml4pd/optimize/__init__.py
ml4pd/optimize/dimension.py
ml4pd/streams/__init__.py
ml4pd/streams/heat_stream.py
ml4pd/streams/material_stream.py
ml4pd/streams/stream.py
ml4pd/streams/utils.py
ml4pd/streams/work_stream.py
ml4pd-2022.11.9.dist-info/LICENSE
ml4pd-2022.11.9.dist-info/METADATA
ml4pd-2022.11.9.dist-info/WHEEL
ml4pd-2022.11.9.dist-info/top_level.txt
ml4pd-2022.11.9.dist-info/RECORD
