Metadata-Version: 2.1
Name: ml4pd
Version: 2022.11.9
Summary: ML4PD - an open-source libray for building Aspen-like process models via machine learning.
Maintainer: Hien Vo
Maintainer-email: nolan.wilson@nrel.gov
Classifier: Programming Language :: Python :: 3.7
Classifier: Programming Language :: Python :: 3.8
Requires-Python: >=3.8
License-File: LICENSE
Requires-Dist: scikit-learn (==1.1.1)
Requires-Dist: lightgbm (==3.3.2)
Requires-Dist: rdkit-pypi (==2022.3.2.1)
Requires-Dist: thermo (==0.2.13)
Requires-Dist: pint
Requires-Dist: pyarrow
Requires-Dist: pydantic
Requires-Dist: networkx
Requires-Dist: graphviz
Requires-Dist: pydot
Provides-Extra: test
Requires-Dist: seaborn ; extra == 'test'
Requires-Dist: ipykernel ; extra == 'test'
Requires-Dist: ipython ; extra == 'test'
Requires-Dist: pytest ; extra == 'test'
Requires-Dist: black ; extra == 'test'
Requires-Dist: pylint ; extra == 'test'
Requires-Dist: tqdm ; extra == 'test'
Requires-Dist: mkdocs-material ; extra == 'test'
Requires-Dist: mkdocs-jupyter ; extra == 'test'
